AUTHORS
LICENSE
MANIFEST.in
README.rst
setup.py
django_url_fullpath_redirect.egg-info/PKG-INFO
django_url_fullpath_redirect.egg-info/SOURCES.txt
django_url_fullpath_redirect.egg-info/dependency_links.txt
django_url_fullpath_redirect.egg-info/requires.txt
django_url_fullpath_redirect.egg-info/top_level.txt
tests/__init__.py
tests/config.py
tests/manage.py
tests/settings.py
tests/urls.py
tests/templates/404.html
url_tracker/__init__.py
url_tracker/admin.py
url_tracker/middleware.py
url_tracker/models.py
url_tracker/tests.py
url_tracker/views.py
url_tracker/migrations/0001_initial.py
url_tracker/migrations/0002_rename_urlchange_to_urlchangerecord.py
url_tracker/migrations/0003_auto__add_unique_urlchangerecord_old_url.py
url_tracker/migrations/__init__.py