Metadata-Version: 1.0
Name: django-url-fullpath-redirect
Version: 0.1.2
Summary: Fork of django-url-tracker with query_string support
Home-page: https://github.com/alifanov/django-url-fullpath-redirect
Author: Lifanov Alexander
Author-email: lifanov.a.v@gmail.com
License: BSD
Keywords: seo,django,framework
Platform: UNKNOWN
Classifier: Development Status :: 3 - Alpha
Classifier: Environment :: Web Environment
Classifier: Framework :: Django
Classifier: Intended Audience :: Developers
Classifier: Programming Language :: Python
Classifier: License :: OSI Approved :: Apache Software License
Classifier: License :: OSI Approved :: BSD License
Classifier: Operating System :: OS Independent
Classifier: Topic :: Software Development
